<annotation verified="yes">
	<folder>l</folder>
	<filename>l_1240.jpg</filename>
	<path>C:\Users\user\Desktop\handlang_data\data_1\l\l_1240.jpg</path>
	<source>
		<database>Unknown</database>
	</source>
	<size>
		<width>100</width>
		<height>59</height>
		<depth>1</depth>
	</size>
	<segmented>0</segmented>
	<object>
		<name>l</name>
		<pose>Unspecified</pose>
		<truncated>0</truncated>
		<difficult>0</difficult>
		<bndbox>
			<xmin>30</xmin>
			<ymin>10</ymin>
			<xmax>86</xmax>
			<ymax>56</ymax>
		</bndbox>
	</object>
</annotation>
